{
  "eventType": "attr_set",
  "specVersion": 4,
  "eventData": {
    "changes": [
      {
        "key": "$eve.type",
        "value": "turn"
      },
      {
        "key": "$eve.parent",
        "value": "wrun_01KVD8KMD6M4PAC88H2JXAYS9M"
      },
      {
        "key": "$eve.root",
        "value": "wrun_01KVD8GP0ZXKQXYVBTJZ22VMFM"
      }
    ],
    "writer": {
      "type": "step",
      "stepId": "step_01KVD8KME35ZH37Y61WW9GGYDK",
      "attempt": 1
    },
    "allowReservedAttributes": true
  },
  "runId": "wrun_01KVD8KME3KTEAF0GKD60Y06YY",
  "eventId": "evnt_01KVD8KMECPCN998466JF8WGYG",
  "createdAt": "2026-06-18T11:42:05.772Z"
}