{
  "eventType": "attr_set",
  "specVersion": 4,
  "eventData": {
    "changes": [
      {
        "key": "$eve.type",
        "value": "turn"
      },
      {
        "key": "$eve.parent",
        "value": "wrun_01KVD9A1PW3N4JF4858E4EHNNK"
      },
      {
        "key": "$eve.root",
        "value": "wrun_01KVD90QRTRP4YDT1V14SK8RN8"
      }
    ],
    "writer": {
      "type": "step",
      "stepId": "step_01KVD9A1RJSZRBJTFCHEQWHMG7",
      "attempt": 1
    },
    "allowReservedAttributes": true
  },
  "runId": "wrun_01KVD9A1RHFGF64Q10AVGY1754",
  "eventId": "evnt_01KVD9A1SV3XGRJECGHHJ1ERJ0",
  "createdAt": "2026-06-18T11:54:20.347Z"
}