{
  "eventType": "attr_set",
  "specVersion": 4,
  "eventData": {
    "changes": [
      {
        "key": "$eve.type",
        "value": "turn"
      },
      {
        "key": "$eve.parent",
        "value": "wrun_01KVD9CXVJ20AKDYWRR4ARTR1Y"
      },
      {
        "key": "$eve.root",
        "value": "wrun_01KVD90QRTRP4YDT1V14SK8RN8"
      }
    ],
    "writer": {
      "type": "step",
      "stepId": "step_01KVD9CXWPKA9TQ6MBG5AWX09D",
      "attempt": 1
    },
    "allowReservedAttributes": true
  },
  "runId": "wrun_01KVD9CXWN2CPP7SSKC91EXM45",
  "eventId": "evnt_01KVD9CXX367Y691CK0M5TRKZH",
  "createdAt": "2026-06-18T11:55:54.659Z"
}